wan/__init__.py
wan/animate.py
wan/image2video.py
wan/speech2video.py
wan/text2video.py
wan/textimage2video.py
wan/configs/__init__.py
wan/configs/shared_config.py
wan/configs/wan_animate_14B.py
wan/configs/wan_i2v_A14B.py
wan/configs/wan_s2v_14B.py
wan/configs/wan_t2v_A14B.py
wan/configs/wan_ti2v_5B.py
wan/distributed/__init__.py
wan/distributed/fsdp.py
wan/distributed/sequence_parallel.py
wan/distributed/ulysses.py
wan/distributed/util.py
wan/modules/__init__.py
wan/modules/attention.py
wan/modules/model.py
wan/modules/t5.py
wan/modules/tokenizers.py
wan/modules/vae2_1.py
wan/modules/vae2_2.py
wan/modules/animate/__init__.py
wan/modules/animate/animate_utils.py
wan/modules/animate/clip.py
wan/modules/animate/face_blocks.py
wan/modules/animate/model_animate.py
wan/modules/animate/motion_encoder.py
wan/modules/animate/xlm_roberta.py
wan/modules/animate/preprocess/__init__.py
wan/modules/animate/preprocess/human_visualization.py
wan/modules/animate/preprocess/pose2d.py
wan/modules/animate/preprocess/pose2d_utils.py
wan/modules/animate/preprocess/preprocess_data.py
wan/modules/animate/preprocess/process_pipepline.py
wan/modules/animate/preprocess/retarget_pose.py
wan/modules/animate/preprocess/sam_utils.py
wan/modules/animate/preprocess/utils.py
wan/modules/animate/preprocess/video_predictor.py
wan/modules/s2v/__init__.py
wan/modules/s2v/audio_encoder.py
wan/modules/s2v/audio_utils.py
wan/modules/s2v/auxi_blocks.py
wan/modules/s2v/model_s2v.py
wan/modules/s2v/motioner.py
wan/modules/s2v/s2v_utils.py
wan/utils/__init__.py
wan/utils/fm_solvers.py
wan/utils/fm_solvers_unipc.py
wan/utils/prompt_extend.py
wan/utils/qwen_vl_utils.py
wan/utils/system_prompt.py
wan/utils/utils.py
wan22-2.2.11.dist-info/licenses/LICENSE.txt
wan22-2.2.11.dist-info/METADATA
wan22-2.2.11.dist-info/WHEEL
wan22-2.2.11.dist-info/top_level.txt
wan22-2.2.11.dist-info/RECORD
